spectrograms/__init__.py
spectrograms/__init__.pyi
spectrograms/_spectrograms.cpython-312-x86_64-linux-gnu.so
spectrograms/py.typed
spectrograms-0.2.3.dist-info/METADATA
spectrograms-0.2.3.dist-info/WHEEL
spectrograms-0.2.3.dist-info/licenses/LICENSE
spectrograms-0.2.3.dist-info/RECORD
