Metadata-Version: 2.4
Name: spectrograms
Version: 0.2.3
Classifier: Programming Language :: Rust
Classifier: Programming Language :: Python :: Implementation :: CPython
Classifier: Programming Language :: Python :: 3
Classifier: Programming Language :: Python :: 3.9
Classifier: Programming Language :: Python :: 3.10
Classifier: Programming Language :: Python :: 3.11
Classifier: Programming Language :: Python :: 3.12
Classifier: Topic :: Multimedia :: Sound/Audio :: Analysis
Classifier: Topic :: Scientific/Engineering
Classifier: License :: OSI Approved :: MIT License
Requires-Dist: numpy>=1.6
License-File: LICENSE
Summary: Fast spectrogram computation library powered by Rust
Keywords: spectrogram,audio,fft,image,signal-processing
Author-email: "Jack Geraghty (jmg049)" <jgeraghty049@gmail.com>
License-Expression: MIT
Requires-Python: >=3.9
Project-URL: Homepage, https://github.com/jmg049/Spectrograms
Project-URL: Issues, https://github.com/jmg049/Spectrograms/issues
Project-URL: Repository, https://github.com/jmg049/Spectrograms
